crcmod_plus-2.3.1.dist-info/RECORD
crcmod_plus-2.3.1.dist-info/WHEEL
crcmod_plus-2.3.1.dist-info/top_level.txt
crcmod_plus-2.3.1.dist-info/METADATA
crcmod_plus-2.3.1.dist-info/licenses/LICENSE.txt
crcmod/_version.py
crcmod/predefined.py
crcmod/__init__.py
crcmod/types.py
crcmod/py.typed
crcmod/crcmod.py
crcmod/_crcfunext.abi3.so
crcmod/_crcfunpy.py
