Metadata-Version: 2.4
Name: crcmod-plus
Version: 2.3.1
Summary: CRC generator - modernized
Author-email: Ray Buvel <rlbuvel@gmail.com>
Maintainer-email: Tamas Nepusz <tamas@sxd.hu>
License-Expression: MIT
Project-URL: Changelog, https://github.com/ntamas/crcmod-plus/blob/main/CHANGELOG.md
Project-URL: Documentation, https://github.com/ntamas/crcmod-plus#readme
Project-URL: Issues, https://github.com/ntamas/crcmod-plus/issues
Project-URL: Source, https://github.com/ntamas/crcmod-plus
Classifier: Development Status :: 5 - Production/Stable
Classifier: Intended Audience :: Developers
Classifier: Intended Audience :: Education
Classifier: Intended Audience :: End Users/Desktop
Classifier: Intended Audience :: Information Technology
Classifier: Intended Audience :: Science/Research
Classifier: Operating System :: OS Independent
Classifier: Programming Language :: C
Classifier: Programming Language :: C++
Classifier: Programming Language :: Python
Classifier: Programming Language :: Python :: 3
Classifier: Programming Language :: Python :: 3.9
Classifier: Programming Language :: Python :: 3.10
Classifier: Programming Language :: Python :: 3.11
Classifier: Programming Language :: Python :: 3.12
Classifier: Programming Language :: Python :: 3.13
Classifier: Programming Language :: Python :: 3.14
Classifier: Topic :: Communications
Classifier: Topic :: Scientific/Engineering :: Interface Engine/Protocol Translator
Classifier: Topic :: Scientific/Engineering :: Mathematics
Classifier: Topic :: Utilities
Requires-Python: >=3.9
License-File: LICENSE.txt
Requires-Dist: typing_extensions; python_version < "3.8"
Provides-Extra: dev
Requires-Dist: pytest; extra == "dev"
Dynamic: license-file
